uniserde/__init__.py
uniserde/bson_deserialize.py
uniserde/bson_serde.py
uniserde/bson_serialize.py
uniserde/case_convert.py
uniserde/codegen.py
uniserde/compat.py
uniserde/errors.py
uniserde/json_deserialize.py
uniserde/json_serde.py
uniserde/json_serialize.py
uniserde/lazy_wrapper.py
uniserde/objectid_proxy.py
uniserde/schema_mongodb.py
uniserde/serde_cache.py
uniserde/type_hint.py
uniserde/typedefs.py
uniserde/utils.py
uniserde-0.4.0.post0.dist-info/METADATA
uniserde-0.4.0.post0.dist-info/WHEEL
uniserde-0.4.0.post0.dist-info/licenses/LICENSE.txt
uniserde-0.4.0.post0.dist-info/RECORD
