Metadata-Version: 2.3
Name: uniserde
Version: 0.4.0.post0
Summary: Convention based, effortless serialization and deserialization
Project-URL: repository, https://gitlab.com/mad-moo/uniserde
Author-email: Jakob Pinterits <jakob.pinterits@gmail.com>
License: Copyright (c) 2025 Jakob Pinterits
Requires-Python: >=3.10
Requires-Dist: python-dateutil<3.0.0,>=2.8.2
Requires-Dist: typing-extensions<5.0.0,>=4.7.1
